setup.cfg
setup.py
Flask_DWConnector.egg-info/PKG-INFO
Flask_DWConnector.egg-info/SOURCES.txt
Flask_DWConnector.egg-info/dependency_links.txt
Flask_DWConnector.egg-info/not-zip-safe
Flask_DWConnector.egg-info/requires.txt
Flask_DWConnector.egg-info/top_level.txt
flask_dwconnector/__init__.py
flask_dwconnector/flask_dwconnector.py