Metadata-Version: 1.1
Name: Flask-DWConnector
Version: 0.0.1
Summary: Use to connect DataWald RESTful API.
Home-page: https://github.com/ideabosque/Flask-DWConnector
Author: Idea Bosque
Author-email: ideabosque@gmail.com
License: MIT
Download-URL: https://github.com/ideabosque/Flask-DWConnector/tarball/0.0.1
Keywords: DataWald
Platform: any
Classifier: License :: OSI Approved :: MIT License
Classifier: Framework :: Flask
Classifier: Programming Language :: Python
Classifier: Environment :: Web Environment
Classifier: Intended Audience :: Developers
Classifier: Operating System :: OS Independent
Classifier: Topic :: Internet :: WWW/HTTP :: Dynamic Content
Classifier: Topic :: Software Development :: Libraries :: Python Modules
